collective/__init__.py
collective/listmonk/__init__.py
collective/listmonk/configure.zcml
collective/listmonk/dependencies.zcml
collective/listmonk/interfaces.py
collective/listmonk/listmonk.py
collective/listmonk/permissions.zcml
collective/listmonk/profiles.zcml
collective/listmonk/testing.py
collective/listmonk/behaviors/__init__.py
collective/listmonk/behaviors/configure.zcml
collective/listmonk/content/__init__.py
collective/listmonk/content/newsletter.py
collective/listmonk/controlpanel/__init__.py
collective/listmonk/controlpanel/configure.zcml
collective/listmonk/locales/__init__.py
collective/listmonk/locales/__main__.py
collective/listmonk/locales/collective.listmonk.pot
collective/listmonk/locales/update.py
collective/listmonk/locales/de/LC_MESSAGES/collective.listmonk.mo
collective/listmonk/locales/de/LC_MESSAGES/collective.listmonk.po
collective/listmonk/locales/en/LC_MESSAGES/collective.listmonk.mo
collective/listmonk/locales/en/LC_MESSAGES/collective.listmonk.po
collective/listmonk/profiles/default/browserlayer.xml
collective/listmonk/profiles/default/metadata.xml
collective/listmonk/profiles/default/rolemap.xml
collective/listmonk/profiles/default/types.xml
collective/listmonk/profiles/default/types/Newsletter.xml
collective/listmonk/profiles/uninstall/browserlayer.xml
collective/listmonk/services/__init__.py
collective/listmonk/services/base.py
collective/listmonk/services/configure.zcml
collective/listmonk/services/mailings.py
collective/listmonk/services/subscriptions.py
collective/listmonk/setuphandlers/__init__.py
collective/listmonk/upgrades/__init__.py
collective/listmonk/upgrades/configure.zcml
collective_listmonk-1.0.0.dist-info/METADATA
collective_listmonk-1.0.0.dist-info/WHEEL
collective_listmonk-1.0.0.dist-info/entry_points.txt
collective_listmonk-1.0.0.dist-info/licenses/LICENSE.GPL
collective_listmonk-1.0.0.dist-info/licenses/LICENSE.md
collective_listmonk-1.0.0.dist-info/RECORD
