Metadata-Version: 2.4
Name: collective.listmonk
Version: 1.0.0
Summary: A Listmonk newsletter integration for Plone.
Project-URL: Homepage, https://github.com/collective/collective.listmonk
Project-URL: PyPI, https://pypi.org/project/collective.listmonk
Project-URL: Source, https://github.com/collective/collective.listmonk
Project-URL: Tracker, https://github.com/collective/collective.listmonk/issues
Author-email: kitconcept GmbH <info@kitconcept.com>
License-Expression: GPL-2.0-only
License-File: LICENSE.GPL
License-File: LICENSE.md
Keywords: CMS,Plone,Python
Classifier: Development Status :: 3 - Alpha
Classifier: Environment :: Web Environment
Classifier: Framework :: Plone
Classifier: Framework :: Plone :: 6.0
Classifier: Framework :: Plone :: 6.1
Classifier: Framework :: Plone :: Addon
Classifier: Operating System :: OS Independent
Classifier: Programming Language :: Python :: 3.11
Classifier: Programming Language :: Python :: 3.12
Classifier: Programming Language :: Python :: 3.13
Requires-Python: >=3.11
Requires-Dist: annotated-types
Requires-Dist: plone-api
Requires-Dist: plone-restapi
Requires-Dist: products-cmfplone
Requires-Dist: pydantic
Requires-Dist: pydantic-settings
Requires-Dist: requests
Requires-Dist: souper-plone
Provides-Extra: release
Requires-Dist: zest-pocompile; extra == 'release'
Requires-Dist: zest-releaser[recommended]; extra == 'release'
Requires-Dist: zestreleaser-towncrier; extra == 'release'
Provides-Extra: test
Requires-Dist: horse-with-no-namespace; extra == 'test'
Requires-Dist: plone-app-testing; extra == 'test'
Requires-Dist: plone-restapi[test]; extra == 'test'
Requires-Dist: plone-volto; extra == 'test'
Requires-Dist: pytest; extra == 'test'
Requires-Dist: pytest-cov; extra == 'test'
Requires-Dist: pytest-plone>=0.5.0; extra == 'test'
